autoreadme-0.2302.3.data/scripts/autoreadme
autoreadme_/__init__.py
autoreadme_/autoreadme.py
autoreadme-0.2302.3.dist-info/LICENSE
autoreadme-0.2302.3.dist-info/METADATA
autoreadme-0.2302.3.dist-info/WHEEL
autoreadme-0.2302.3.dist-info/top_level.txt
autoreadme-0.2302.3.dist-info/RECORD
