Metadata-Version: 2.1
Name: autoreadme
Version: 0.2302.3
Summary: Generate READMEs with collapsable* code and corresponding output from Python
Home-page: https://github.com/davips/autoreadme
Download-URL: https://github.com/davips/autoreadme/releases
Author: Davi Pereira-Santos
Author-email: dpsabc@gmail.com
License: GPL3
Classifier: Intended Audience :: Science/Research
Classifier: License :: OSI Approved :: GNU General Public License v3 (GPLv3)
Classifier: Natural Language :: English
Classifier: Programming Language :: Python
Classifier: Topic :: Scientific/Engineering
Classifier: Programming Language :: Python :: 3.8
License-File: LICENSE
